data_utilities/__init__.py
data_utilities/matplotlib_utilities.py
data_utilities/pandas_utilities.py
data_utilities/python_utilities.py
data_utilities/tests/__init__.py
data_utilities/tests/test_matplotlib_utilities.py
data_utilities/tests/test_pandas_utilities.py
data_utilities/tests/test_python_utilities.py
data_utilities/tests/test_support.py
data_utilities-1.2.7.dist-info/DESCRIPTION.rst
data_utilities-1.2.7.dist-info/METADATA
data_utilities-1.2.7.dist-info/RECORD
data_utilities-1.2.7.dist-info/WHEEL
data_utilities-1.2.7.dist-info/metadata.json
data_utilities-1.2.7.dist-info/top_level.txt
