Metadata-Version: 2.0
Name: data-utilities
Version: 1.2.7
Summary: A data analysis and visualization helper module.
Home-page: https://github.com/fmv1992/data_utilities
Author: Felipe M. Vieira
Author-email: fmv.profissional@gmail.com
License: GPLv2 or any later
Keywords: data sciences
Platform: UNKNOWN
Classifier: Development Status :: 3 - Alpha
Classifier: Intended Audience :: End Users/Desktop
Classifier: Topic :: Scientific/Engineering :: Information Analysis
Classifier: License :: OSI Approved :: GNU General Public License v3 (GPLv3)
Classifier: Programming Language :: Python :: 3.4
Classifier: Programming Language :: Python :: 3.6
Requires-Dist: numpy
Requires-Dist: scipy
Requires-Dist: pandas
Requires-Dist: matplotlib
Requires-Dist: seaborn
Requires-Dist: scikit-learn
